pytest_cratedb/plugin.py
pytest_cratedb-0.4.1.dist-info/licenses/LICENSE
pytest_cratedb-0.4.1.dist-info/METADATA
pytest_cratedb-0.4.1.dist-info/WHEEL
pytest_cratedb-0.4.1.dist-info/entry_points.txt
pytest_cratedb-0.4.1.dist-info/top_level.txt
pytest_cratedb-0.4.1.dist-info/RECORD
